{
  "topic": "Linked List",
  "totalProblems": 13,
  "difficultyBreakdown": {
    "Easy": 2,
    "Medium": 5,
    "Hard": 2
  },
  "patternBreakdown": {
    "Monotonic Stack/Queue": 1,
    "In-Place Linked List Reversal": 5,
    "Two Pointers": 7
  },
  "problems": [
    {
      "id": "leetcode-remove-nodes-from-linked-list",
      "title": "Remove Nodes From Linked List",
      "platform": "LeetCode",
      "difficulty": "Easy",
      "url": "https://leetcode.com/problems/remove-nodes-from-linked-list/",
      "urlGenerated": false,
      "primaryTopic": "Linked List",
      "pattern": "Monotonic Stack/Queue",
      "notes": null,
      "metadata": {
        "companies": [],
        "frequency": null,
        "sources": [
          "dsa-patterns-cheat-sheet"
        ]
      },
      "progress": {
        "completed": false,
        "attemptedButNotSolved": false,
        "hasSolution": false,
        "hasOptimalSolution": false,
        "understoodCompletely": false,
        "needsReview": false,
        "solvedOnce": false,
        "solvedTwice": false,
        "solvedThreePlus": false,
        "bookmarked": false,
        "isFavorite": false,
        "watchedVideoSolution": false,
        "readEditorialSolution": false,
        "solvedInTime": false,
        "needsSpeedImprovement": false,
        "canExplainToOthers": false,
        "interviewReady": false,
        "markedForRevision": false,
        "revisedOnce": false,
        "revisedMultipleTimes": false,
        "easierThanRated": false,
        "harderThanRated": false,
        "hasNotes": false,
        "hasCustomTags": false
      },
      "timestamps": {
        "firstAttemptedAt": null,
        "lastAttemptedAt": null,
        "completedAt": null,
        "lastReviewedAt": null,
        "addedToFavoritesAt": null
      },
      "userData": {
        "notes": "",
        "customTags": [],
        "timeTaken": null,
        "attemptCount": 0,
        "personalDifficultyRating": null,
        "confidenceLevel": null,
        "solutionLinks": [],
        "resourceLinks": [],
        "mistakesMade": [],
        "keyInsights": []
      }
    },
    {
      "id": "leetcode-reverse-linked-list",
      "title": "Reverse Linked List",
      "platform": "LeetCode",
      "difficulty": "Easy",
      "url": "https://leetcode.com/problems/reverse-linked-list/",
      "urlGenerated": false,
      "primaryTopic": "Linked List",
      "pattern": "In-Place Linked List Reversal",
      "notes": "Iterative solution, Recursive solution\n\niterate through maintaining cur and prev; recursively reverse, return new head of list",
      "metadata": {
        "companies": [],
        "frequency": null,
        "sources": [
          "Aryan-dsa-160",
          "blind-75",
          "dsa-patterns-cheat-sheet",
          "grind-75",
          "neetcode-150"
        ]
      },
      "progress": {
        "completed": false,
        "attemptedButNotSolved": false,
        "hasSolution": false,
        "hasOptimalSolution": false,
        "understoodCompletely": false,
        "needsReview": false,
        "solvedOnce": false,
        "solvedTwice": false,
        "solvedThreePlus": false,
        "bookmarked": false,
        "isFavorite": false,
        "watchedVideoSolution": false,
        "readEditorialSolution": false,
        "solvedInTime": false,
        "needsSpeedImprovement": false,
        "canExplainToOthers": false,
        "interviewReady": false,
        "markedForRevision": false,
        "revisedOnce": false,
        "revisedMultipleTimes": false,
        "easierThanRated": false,
        "harderThanRated": false,
        "hasNotes": false,
        "hasCustomTags": false
      },
      "timestamps": {
        "firstAttemptedAt": null,
        "lastAttemptedAt": null,
        "completedAt": null,
        "lastReviewedAt": null,
        "addedToFavoritesAt": null
      },
      "userData": {
        "notes": "",
        "customTags": [],
        "timeTaken": null,
        "attemptCount": 0,
        "personalDifficultyRating": null,
        "confidenceLevel": null,
        "solutionLinks": [],
        "resourceLinks": [],
        "mistakesMade": [],
        "keyInsights": []
      }
    },
    {
      "id": "leetcode-copy-list-with-random-pointer",
      "title": "Copy List with Random Pointer",
      "platform": "LeetCode",
      "difficulty": "Medium",
      "url": "https://leetcode.com/problems/copy-list-with-random-pointer/",
      "urlGenerated": false,
      "primaryTopic": "Linked List",
      "pattern": "Two Pointers",
      "notes": "Day 5",
      "metadata": {
        "companies": [
          "Amazon"
        ],
        "frequency": null,
        "sources": [
          "Aryan-dsa-160",
          "amazon-sde-riddhi-dutta",
          "neetcode-150"
        ],
        "importance": "VVVI",
        "day": 5
      },
      "progress": {
        "completed": false,
        "attemptedButNotSolved": false,
        "hasSolution": false,
        "hasOptimalSolution": false,
        "understoodCompletely": false,
        "needsReview": false,
        "solvedOnce": false,
        "solvedTwice": false,
        "solvedThreePlus": false,
        "bookmarked": false,
        "isFavorite": false,
        "watchedVideoSolution": false,
        "readEditorialSolution": false,
        "solvedInTime": false,
        "needsSpeedImprovement": false,
        "canExplainToOthers": false,
        "interviewReady": false,
        "markedForRevision": false,
        "revisedOnce": false,
        "revisedMultipleTimes": false,
        "easierThanRated": false,
        "harderThanRated": false,
        "hasNotes": false,
        "hasCustomTags": false
      },
      "timestamps": {
        "firstAttemptedAt": null,
        "lastAttemptedAt": null,
        "completedAt": null,
        "lastReviewedAt": null,
        "addedToFavoritesAt": null
      },
      "userData": {
        "notes": "",
        "customTags": [],
        "timeTaken": null,
        "attemptCount": 0,
        "personalDifficultyRating": null,
        "confidenceLevel": null,
        "solutionLinks": [],
        "resourceLinks": [],
        "mistakesMade": [],
        "keyInsights": []
      }
    },
    {
      "id": "leetcode-insertion-sort-list",
      "title": "Insertion Sort List",
      "platform": "LeetCode",
      "difficulty": "Medium",
      "url": "https://www.google.com/search?q=Insertion+Sort+List+LeetCode",
      "urlGenerated": true,
      "primaryTopic": "Linked List",
      "pattern": "Two Pointers",
      "notes": "Insertion Sort",
      "metadata": {
        "companies": [],
        "frequency": null,
        "sources": [
          "Aryan-dsa-160"
        ]
      },
      "progress": {
        "completed": false,
        "attemptedButNotSolved": false,
        "hasSolution": false,
        "hasOptimalSolution": false,
        "understoodCompletely": false,
        "needsReview": false,
        "solvedOnce": false,
        "solvedTwice": false,
        "solvedThreePlus": false,
        "bookmarked": false,
        "isFavorite": false,
        "watchedVideoSolution": false,
        "readEditorialSolution": false,
        "solvedInTime": false,
        "needsSpeedImprovement": false,
        "canExplainToOthers": false,
        "interviewReady": false,
        "markedForRevision": false,
        "revisedOnce": false,
        "revisedMultipleTimes": false,
        "easierThanRated": false,
        "harderThanRated": false,
        "hasNotes": false,
        "hasCustomTags": false
      },
      "timestamps": {
        "firstAttemptedAt": null,
        "lastAttemptedAt": null,
        "completedAt": null,
        "lastReviewedAt": null,
        "addedToFavoritesAt": null
      },
      "userData": {
        "notes": "",
        "customTags": [],
        "timeTaken": null,
        "attemptCount": 0,
        "personalDifficultyRating": null,
        "confidenceLevel": null,
        "solutionLinks": [],
        "resourceLinks": [],
        "mistakesMade": [],
        "keyInsights": []
      }
    },
    {
      "id": "leetcode-reverse-a-sub-list",
      "title": "Reverse a Sub-list",
      "platform": "LeetCode",
      "difficulty": "Medium",
      "url": "https://leetcode.com/problems/reverse-linked-list-ii/",
      "urlGenerated": false,
      "primaryTopic": "Linked List",
      "pattern": "In-Place Linked List Reversal",
      "notes": null,
      "metadata": {
        "companies": [],
        "frequency": null,
        "sources": [
          "dsa-patterns-cheat-sheet"
        ]
      },
      "progress": {
        "completed": false,
        "attemptedButNotSolved": false,
        "hasSolution": false,
        "hasOptimalSolution": false,
        "understoodCompletely": false,
        "needsReview": false,
        "solvedOnce": false,
        "solvedTwice": false,
        "solvedThreePlus": false,
        "bookmarked": false,
        "isFavorite": false,
        "watchedVideoSolution": false,
        "readEditorialSolution": false,
        "solvedInTime": false,
        "needsSpeedImprovement": false,
        "canExplainToOthers": false,
        "interviewReady": false,
        "markedForRevision": false,
        "revisedOnce": false,
        "revisedMultipleTimes": false,
        "easierThanRated": false,
        "harderThanRated": false,
        "hasNotes": false,
        "hasCustomTags": false
      },
      "timestamps": {
        "firstAttemptedAt": null,
        "lastAttemptedAt": null,
        "completedAt": null,
        "lastReviewedAt": null,
        "addedToFavoritesAt": null
      },
      "userData": {
        "notes": "",
        "customTags": [],
        "timeTaken": null,
        "attemptCount": 0,
        "personalDifficultyRating": null,
        "confidenceLevel": null,
        "solutionLinks": [],
        "resourceLinks": [],
        "mistakesMade": [],
        "keyInsights": []
      }
    },
    {
      "id": "leetcode-reverse-list-in-pairs",
      "title": "Reverse List in Pairs",
      "platform": "LeetCode",
      "difficulty": "Medium",
      "url": "https://leetcode.com/problems/swap-nodes-in-pairs/description/",
      "urlGenerated": false,
      "primaryTopic": "Linked List",
      "pattern": "In-Place Linked List Reversal",
      "notes": null,
      "metadata": {
        "companies": [],
        "frequency": null,
        "sources": [
          "dsa-patterns-cheat-sheet"
        ]
      },
      "progress": {
        "completed": false,
        "attemptedButNotSolved": false,
        "hasSolution": false,
        "hasOptimalSolution": false,
        "understoodCompletely": false,
        "needsReview": false,
        "solvedOnce": false,
        "solvedTwice": false,
        "solvedThreePlus": false,
        "bookmarked": false,
        "isFavorite": false,
        "watchedVideoSolution": false,
        "readEditorialSolution": false,
        "solvedInTime": false,
        "needsSpeedImprovement": false,
        "canExplainToOthers": false,
        "interviewReady": false,
        "markedForRevision": false,
        "revisedOnce": false,
        "revisedMultipleTimes": false,
        "easierThanRated": false,
        "harderThanRated": false,
        "hasNotes": false,
        "hasCustomTags": false
      },
      "timestamps": {
        "firstAttemptedAt": null,
        "lastAttemptedAt": null,
        "completedAt": null,
        "lastReviewedAt": null,
        "addedToFavoritesAt": null
      },
      "userData": {
        "notes": "",
        "customTags": [],
        "timeTaken": null,
        "attemptCount": 0,
        "personalDifficultyRating": null,
        "confidenceLevel": null,
        "solutionLinks": [],
        "resourceLinks": [],
        "mistakesMade": [],
        "keyInsights": []
      }
    },
    {
      "id": "leetcode-rotate-a-linkedlist",
      "title": "Rotate a LinkedList",
      "platform": "LeetCode",
      "difficulty": "Medium",
      "url": "https://leetcode.com/problems/rotate-list/",
      "urlGenerated": false,
      "primaryTopic": "Linked List",
      "pattern": "Two Pointers",
      "notes": "Problem Challenge 2",
      "metadata": {
        "companies": [],
        "frequency": null,
        "sources": [
          "dsa-patterns-cheat-sheet"
        ]
      },
      "progress": {
        "completed": false,
        "attemptedButNotSolved": false,
        "hasSolution": false,
        "hasOptimalSolution": false,
        "understoodCompletely": false,
        "needsReview": false,
        "solvedOnce": false,
        "solvedTwice": false,
        "solvedThreePlus": false,
        "bookmarked": false,
        "isFavorite": false,
        "watchedVideoSolution": false,
        "readEditorialSolution": false,
        "solvedInTime": false,
        "needsSpeedImprovement": false,
        "canExplainToOthers": false,
        "interviewReady": false,
        "markedForRevision": false,
        "revisedOnce": false,
        "revisedMultipleTimes": false,
        "easierThanRated": false,
        "harderThanRated": false,
        "hasNotes": false,
        "hasCustomTags": false
      },
      "timestamps": {
        "firstAttemptedAt": null,
        "lastAttemptedAt": null,
        "completedAt": null,
        "lastReviewedAt": null,
        "addedToFavoritesAt": null
      },
      "userData": {
        "notes": "",
        "customTags": [],
        "timeTaken": null,
        "attemptCount": 0,
        "personalDifficultyRating": null,
        "confidenceLevel": null,
        "solutionLinks": [],
        "resourceLinks": [],
        "mistakesMade": [],
        "keyInsights": []
      }
    },
    {
      "id": "leetcode-reverse-node-in-k-group",
      "title": "Reverse Node in k-Group",
      "platform": "LeetCode",
      "difficulty": "Hard",
      "url": "https://leetcode.com/problems/reverse-nodes-in-k-group/",
      "urlGenerated": false,
      "primaryTopic": "Linked List",
      "pattern": "In-Place Linked List Reversal",
      "notes": "Iterative solution, Recursive solution\n\nDay 5",
      "metadata": {
        "companies": [
          "Amazon"
        ],
        "frequency": null,
        "sources": [
          "Aryan-dsa-160",
          "amazon-sde-riddhi-dutta",
          "dsa-patterns-cheat-sheet",
          "neetcode-150"
        ],
        "importance": "VVVI",
        "day": 5
      },
      "progress": {
        "completed": false,
        "attemptedButNotSolved": false,
        "hasSolution": false,
        "hasOptimalSolution": false,
        "understoodCompletely": false,
        "needsReview": false,
        "solvedOnce": false,
        "solvedTwice": false,
        "solvedThreePlus": false,
        "bookmarked": false,
        "isFavorite": false,
        "watchedVideoSolution": false,
        "readEditorialSolution": false,
        "solvedInTime": false,
        "needsSpeedImprovement": false,
        "canExplainToOthers": false,
        "interviewReady": false,
        "markedForRevision": false,
        "revisedOnce": false,
        "revisedMultipleTimes": false,
        "easierThanRated": false,
        "harderThanRated": false,
        "hasNotes": false,
        "hasCustomTags": false
      },
      "timestamps": {
        "firstAttemptedAt": null,
        "lastAttemptedAt": null,
        "completedAt": null,
        "lastReviewedAt": null,
        "addedToFavoritesAt": null
      },
      "userData": {
        "notes": "",
        "customTags": [],
        "timeTaken": null,
        "attemptCount": 0,
        "personalDifficultyRating": null,
        "confidenceLevel": null,
        "solutionLinks": [],
        "resourceLinks": [],
        "mistakesMade": [],
        "keyInsights": []
      }
    },
    {
      "id": "leetcode-reverse-nodes-in-even-length-groups",
      "title": "Reverse nodes in EVEN Length Groups",
      "platform": "LeetCode",
      "difficulty": "Hard",
      "url": "https://leetcode.com/problems/reverse-nodes-in-even-length-groups/description/",
      "urlGenerated": false,
      "primaryTopic": "Linked List",
      "pattern": "In-Place Linked List Reversal",
      "notes": "Problem Challenge 1",
      "metadata": {
        "companies": [],
        "frequency": null,
        "sources": [
          "dsa-patterns-cheat-sheet"
        ]
      },
      "progress": {
        "completed": false,
        "attemptedButNotSolved": false,
        "hasSolution": false,
        "hasOptimalSolution": false,
        "understoodCompletely": false,
        "needsReview": false,
        "solvedOnce": false,
        "solvedTwice": false,
        "solvedThreePlus": false,
        "bookmarked": false,
        "isFavorite": false,
        "watchedVideoSolution": false,
        "readEditorialSolution": false,
        "solvedInTime": false,
        "needsSpeedImprovement": false,
        "canExplainToOthers": false,
        "interviewReady": false,
        "markedForRevision": false,
        "revisedOnce": false,
        "revisedMultipleTimes": false,
        "easierThanRated": false,
        "harderThanRated": false,
        "hasNotes": false,
        "hasCustomTags": false
      },
      "timestamps": {
        "firstAttemptedAt": null,
        "lastAttemptedAt": null,
        "completedAt": null,
        "lastReviewedAt": null,
        "addedToFavoritesAt": null
      },
      "userData": {
        "notes": "",
        "customTags": [],
        "timeTaken": null,
        "attemptCount": 0,
        "personalDifficultyRating": null,
        "confidenceLevel": null,
        "solutionLinks": [],
        "resourceLinks": [],
        "mistakesMade": [],
        "keyInsights": []
      }
    },
    {
      "id": "leetcode-add-two-numbers",
      "title": "Add Two Numbers",
      "platform": "LeetCode",
      "difficulty": null,
      "url": "https://leetcode.com/problems/add-two-numbers/",
      "urlGenerated": false,
      "primaryTopic": "Linked List",
      "pattern": "Two Pointers",
      "notes": null,
      "metadata": {
        "companies": [],
        "frequency": null,
        "sources": [
          "neetcode-150"
        ]
      },
      "progress": {
        "completed": false,
        "attemptedButNotSolved": false,
        "hasSolution": false,
        "hasOptimalSolution": false,
        "understoodCompletely": false,
        "needsReview": false,
        "solvedOnce": false,
        "solvedTwice": false,
        "solvedThreePlus": false,
        "bookmarked": false,
        "isFavorite": false,
        "watchedVideoSolution": false,
        "readEditorialSolution": false,
        "solvedInTime": false,
        "needsSpeedImprovement": false,
        "canExplainToOthers": false,
        "interviewReady": false,
        "markedForRevision": false,
        "revisedOnce": false,
        "revisedMultipleTimes": false,
        "easierThanRated": false,
        "harderThanRated": false,
        "hasNotes": false,
        "hasCustomTags": false
      },
      "timestamps": {
        "firstAttemptedAt": null,
        "lastAttemptedAt": null,
        "completedAt": null,
        "lastReviewedAt": null,
        "addedToFavoritesAt": null
      },
      "userData": {
        "notes": "",
        "customTags": [],
        "timeTaken": null,
        "attemptCount": 0,
        "personalDifficultyRating": null,
        "confidenceLevel": null,
        "solutionLinks": [],
        "resourceLinks": [],
        "mistakesMade": [],
        "keyInsights": []
      }
    },
    {
      "id": "leetcode-intersection-of-two-linked-lists",
      "title": "Intersection of Two Linked Lists",
      "platform": "LeetCode",
      "difficulty": null,
      "url": "https://leetcode.com/problems/intersection-of-two-linked-lists/",
      "urlGenerated": false,
      "primaryTopic": "Linked List",
      "pattern": "Two Pointers",
      "notes": "Day 15",
      "metadata": {
        "companies": [
          "Amazon"
        ],
        "frequency": null,
        "day": 15,
        "importance": "VVI",
        "sources": [
          "amazon-sde-riddhi-dutta"
        ]
      },
      "progress": {
        "completed": false,
        "attemptedButNotSolved": false,
        "hasSolution": false,
        "hasOptimalSolution": false,
        "understoodCompletely": false,
        "needsReview": false,
        "solvedOnce": false,
        "solvedTwice": false,
        "solvedThreePlus": false,
        "bookmarked": false,
        "isFavorite": false,
        "watchedVideoSolution": false,
        "readEditorialSolution": false,
        "solvedInTime": false,
        "needsSpeedImprovement": false,
        "canExplainToOthers": false,
        "interviewReady": false,
        "markedForRevision": false,
        "revisedOnce": false,
        "revisedMultipleTimes": false,
        "easierThanRated": false,
        "harderThanRated": false,
        "hasNotes": false,
        "hasCustomTags": false
      },
      "timestamps": {
        "firstAttemptedAt": null,
        "lastAttemptedAt": null,
        "completedAt": null,
        "lastReviewedAt": null,
        "addedToFavoritesAt": null
      },
      "userData": {
        "notes": "",
        "customTags": [],
        "timeTaken": null,
        "attemptCount": 0,
        "personalDifficultyRating": null,
        "confidenceLevel": null,
        "solutionLinks": [],
        "resourceLinks": [],
        "mistakesMade": [],
        "keyInsights": []
      }
    },
    {
      "id": "leetcode-merge-two-linked-lists",
      "title": "Merge Two Linked Lists",
      "platform": "LeetCode",
      "difficulty": null,
      "url": "https://leetcode.com/problems/merge-two-sorted-lists/",
      "urlGenerated": false,
      "primaryTopic": "Linked List",
      "pattern": "Two Pointers",
      "notes": null,
      "metadata": {
        "companies": [],
        "frequency": null,
        "sources": [
          "neetcode-150"
        ]
      },
      "progress": {
        "completed": false,
        "attemptedButNotSolved": false,
        "hasSolution": false,
        "hasOptimalSolution": false,
        "understoodCompletely": false,
        "needsReview": false,
        "solvedOnce": false,
        "solvedTwice": false,
        "solvedThreePlus": false,
        "bookmarked": false,
        "isFavorite": false,
        "watchedVideoSolution": false,
        "readEditorialSolution": false,
        "solvedInTime": false,
        "needsSpeedImprovement": false,
        "canExplainToOthers": false,
        "interviewReady": false,
        "markedForRevision": false,
        "revisedOnce": false,
        "revisedMultipleTimes": false,
        "easierThanRated": false,
        "harderThanRated": false,
        "hasNotes": false,
        "hasCustomTags": false
      },
      "timestamps": {
        "firstAttemptedAt": null,
        "lastAttemptedAt": null,
        "completedAt": null,
        "lastReviewedAt": null,
        "addedToFavoritesAt": null
      },
      "userData": {
        "notes": "",
        "customTags": [],
        "timeTaken": null,
        "attemptCount": 0,
        "personalDifficultyRating": null,
        "confidenceLevel": null,
        "solutionLinks": [],
        "resourceLinks": [],
        "mistakesMade": [],
        "keyInsights": []
      }
    },
    {
      "id": "interviewbit-swap-list-nodes-in-pairs",
      "title": "Swap List Nodes in Pairs",
      "platform": "InterviewBit",
      "difficulty": null,
      "url": "https://www.interviewbit.com/problems/swap-list-nodes-in-pairs/",
      "urlGenerated": false,
      "primaryTopic": "Linked List",
      "pattern": "Two Pointers",
      "notes": "Day 16",
      "metadata": {
        "companies": [
          "Amazon"
        ],
        "frequency": null,
        "day": 16,
        "importance": null,
        "sources": [
          "amazon-sde-riddhi-dutta"
        ]
      },
      "progress": {
        "completed": false,
        "attemptedButNotSolved": false,
        "hasSolution": false,
        "hasOptimalSolution": false,
        "understoodCompletely": false,
        "needsReview": false,
        "solvedOnce": false,
        "solvedTwice": false,
        "solvedThreePlus": false,
        "bookmarked": false,
        "isFavorite": false,
        "watchedVideoSolution": false,
        "readEditorialSolution": false,
        "solvedInTime": false,
        "needsSpeedImprovement": false,
        "canExplainToOthers": false,
        "interviewReady": false,
        "markedForRevision": false,
        "revisedOnce": false,
        "revisedMultipleTimes": false,
        "easierThanRated": false,
        "harderThanRated": false,
        "hasNotes": false,
        "hasCustomTags": false
      },
      "timestamps": {
        "firstAttemptedAt": null,
        "lastAttemptedAt": null,
        "completedAt": null,
        "lastReviewedAt": null,
        "addedToFavoritesAt": null
      },
      "userData": {
        "notes": "",
        "customTags": [],
        "timeTaken": null,
        "attemptCount": 0,
        "personalDifficultyRating": null,
        "confidenceLevel": null,
        "solutionLinks": [],
        "resourceLinks": [],
        "mistakesMade": [],
        "keyInsights": []
      }
    }
  ]
}