{
  "topic": "Sorting",
  "totalProblems": 8,
  "difficultyBreakdown": {
    "Easy": 2,
    "Medium": 4,
    "Hard": 2
  },
  "patternBreakdown": {
    "Two Pointers": 2,
    "Hash Maps": 1,
    "Divide and Conquer": 3,
    "Top K Elements": 2
  },
  "problems": [
    {
      "id": "leetcode-merge-sorted-array",
      "title": "Merge Sorted Array",
      "platform": "LeetCode",
      "difficulty": "Easy",
      "url": "https://www.geeksforgeeks.org/problems/merge-k-sorted-arrays/1",
      "urlGenerated": false,
      "primaryTopic": "Sorting",
      "pattern": "Two Pointers",
      "notes": "Selection Sort\n\nHeap as pointer",
      "metadata": {
        "companies": [],
        "frequency": null,
        "sources": [
          "Aryan-dsa-160",
          "dsa-patterns-cheat-sheet"
        ]
      },
      "progress": {
        "completed": false,
        "attemptedButNotSolved": false,
        "hasSolution": false,
        "hasOptimalSolution": false,
        "understoodCompletely": false,
        "needsReview": false,
        "solvedOnce": false,
        "solvedTwice": false,
        "solvedThreePlus": false,
        "bookmarked": false,
        "isFavorite": false,
        "watchedVideoSolution": false,
        "readEditorialSolution": false,
        "solvedInTime": false,
        "needsSpeedImprovement": false,
        "canExplainToOthers": false,
        "interviewReady": false,
        "markedForRevision": false,
        "revisedOnce": false,
        "revisedMultipleTimes": false,
        "easierThanRated": false,
        "harderThanRated": false,
        "hasNotes": false,
        "hasCustomTags": false
      },
      "timestamps": {
        "firstAttemptedAt": null,
        "lastAttemptedAt": null,
        "completedAt": null,
        "lastReviewedAt": null,
        "addedToFavoritesAt": null
      },
      "userData": {
        "notes": "",
        "customTags": [],
        "timeTaken": null,
        "attemptCount": 0,
        "personalDifficultyRating": null,
        "confidenceLevel": null,
        "solutionLinks": [],
        "resourceLinks": [],
        "mistakesMade": [],
        "keyInsights": []
      }
    },
    {
      "id": "leetcode-relative-sort-array",
      "title": "Relative Sort Array",
      "platform": "LeetCode",
      "difficulty": "Easy",
      "url": "https://www.google.com/search?q=Relative+Sort+Array+LeetCode",
      "urlGenerated": true,
      "primaryTopic": "Sorting",
      "pattern": "Hash Maps",
      "notes": "Counting Sort",
      "metadata": {
        "companies": [],
        "frequency": null,
        "sources": [
          "Aryan-dsa-160"
        ]
      },
      "progress": {
        "completed": false,
        "attemptedButNotSolved": false,
        "hasSolution": false,
        "hasOptimalSolution": false,
        "understoodCompletely": false,
        "needsReview": false,
        "solvedOnce": false,
        "solvedTwice": false,
        "solvedThreePlus": false,
        "bookmarked": false,
        "isFavorite": false,
        "watchedVideoSolution": false,
        "readEditorialSolution": false,
        "solvedInTime": false,
        "needsSpeedImprovement": false,
        "canExplainToOthers": false,
        "interviewReady": false,
        "markedForRevision": false,
        "revisedOnce": false,
        "revisedMultipleTimes": false,
        "easierThanRated": false,
        "harderThanRated": false,
        "hasNotes": false,
        "hasCustomTags": false
      },
      "timestamps": {
        "firstAttemptedAt": null,
        "lastAttemptedAt": null,
        "completedAt": null,
        "lastReviewedAt": null,
        "addedToFavoritesAt": null
      },
      "userData": {
        "notes": "",
        "customTags": [],
        "timeTaken": null,
        "attemptCount": 0,
        "personalDifficultyRating": null,
        "confidenceLevel": null,
        "solutionLinks": [],
        "resourceLinks": [],
        "mistakesMade": [],
        "keyInsights": []
      }
    },
    {
      "id": "leetcode-find-duplicates-in-an-array",
      "title": "Find Duplicates in an Array",
      "platform": "LeetCode",
      "difficulty": "Medium",
      "url": "https://www.google.com/search?q=Find+Duplicates+in+an+Array+LeetCode",
      "urlGenerated": true,
      "primaryTopic": "Sorting",
      "pattern": "Divide and Conquer",
      "notes": null,
      "metadata": {
        "companies": [],
        "frequency": null,
        "sources": [
          "Aryan-dsa-160"
        ]
      },
      "progress": {
        "completed": false,
        "attemptedButNotSolved": false,
        "hasSolution": false,
        "hasOptimalSolution": false,
        "understoodCompletely": false,
        "needsReview": false,
        "solvedOnce": false,
        "solvedTwice": false,
        "solvedThreePlus": false,
        "bookmarked": false,
        "isFavorite": false,
        "watchedVideoSolution": false,
        "readEditorialSolution": false,
        "solvedInTime": false,
        "needsSpeedImprovement": false,
        "canExplainToOthers": false,
        "interviewReady": false,
        "markedForRevision": false,
        "revisedOnce": false,
        "revisedMultipleTimes": false,
        "easierThanRated": false,
        "harderThanRated": false,
        "hasNotes": false,
        "hasCustomTags": false
      },
      "timestamps": {
        "firstAttemptedAt": null,
        "lastAttemptedAt": null,
        "completedAt": null,
        "lastReviewedAt": null,
        "addedToFavoritesAt": null
      },
      "userData": {
        "notes": "",
        "customTags": [],
        "timeTaken": null,
        "attemptCount": 0,
        "personalDifficultyRating": null,
        "confidenceLevel": null,
        "solutionLinks": [],
        "resourceLinks": [],
        "mistakesMade": [],
        "keyInsights": []
      }
    },
    {
      "id": "leetcode-sort-an-array",
      "title": "Sort an Array",
      "platform": "LeetCode",
      "difficulty": "Medium",
      "url": "https://www.google.com/search?q=Sort+an+Array+LeetCode",
      "urlGenerated": true,
      "primaryTopic": "Sorting",
      "pattern": "Divide and Conquer",
      "notes": "Merge Sort",
      "metadata": {
        "companies": [],
        "frequency": null,
        "sources": [
          "Aryan-dsa-160"
        ]
      },
      "progress": {
        "completed": false,
        "attemptedButNotSolved": false,
        "hasSolution": false,
        "hasOptimalSolution": false,
        "understoodCompletely": false,
        "needsReview": false,
        "solvedOnce": false,
        "solvedTwice": false,
        "solvedThreePlus": false,
        "bookmarked": false,
        "isFavorite": false,
        "watchedVideoSolution": false,
        "readEditorialSolution": false,
        "solvedInTime": false,
        "needsSpeedImprovement": false,
        "canExplainToOthers": false,
        "interviewReady": false,
        "markedForRevision": false,
        "revisedOnce": false,
        "revisedMultipleTimes": false,
        "easierThanRated": false,
        "harderThanRated": false,
        "hasNotes": false,
        "hasCustomTags": false
      },
      "timestamps": {
        "firstAttemptedAt": null,
        "lastAttemptedAt": null,
        "completedAt": null,
        "lastReviewedAt": null,
        "addedToFavoritesAt": null
      },
      "userData": {
        "notes": "",
        "customTags": [],
        "timeTaken": null,
        "attemptCount": 0,
        "personalDifficultyRating": null,
        "confidenceLevel": null,
        "solutionLinks": [],
        "resourceLinks": [],
        "mistakesMade": [],
        "keyInsights": []
      }
    },
    {
      "id": "leetcode-sort-colors",
      "title": "Sort Colors",
      "platform": "LeetCode",
      "difficulty": "Medium",
      "url": "https://www.google.com/search?q=Sort+Colors+LeetCode",
      "urlGenerated": true,
      "primaryTopic": "Sorting",
      "pattern": "Two Pointers",
      "notes": "Bubble Sort",
      "metadata": {
        "companies": [],
        "frequency": null,
        "sources": [
          "Aryan-dsa-160"
        ]
      },
      "progress": {
        "completed": false,
        "attemptedButNotSolved": false,
        "hasSolution": false,
        "hasOptimalSolution": false,
        "understoodCompletely": false,
        "needsReview": false,
        "solvedOnce": false,
        "solvedTwice": false,
        "solvedThreePlus": false,
        "bookmarked": false,
        "isFavorite": false,
        "watchedVideoSolution": false,
        "readEditorialSolution": false,
        "solvedInTime": false,
        "needsSpeedImprovement": false,
        "canExplainToOthers": false,
        "interviewReady": false,
        "markedForRevision": false,
        "revisedOnce": false,
        "revisedMultipleTimes": false,
        "easierThanRated": false,
        "harderThanRated": false,
        "hasNotes": false,
        "hasCustomTags": false
      },
      "timestamps": {
        "firstAttemptedAt": null,
        "lastAttemptedAt": null,
        "completedAt": null,
        "lastReviewedAt": null,
        "addedToFavoritesAt": null
      },
      "userData": {
        "notes": "",
        "customTags": [],
        "timeTaken": null,
        "attemptCount": 0,
        "personalDifficultyRating": null,
        "confidenceLevel": null,
        "solutionLinks": [],
        "resourceLinks": [],
        "mistakesMade": [],
        "keyInsights": []
      }
    },
    {
      "id": "leetcode-top-k-frequent-elements",
      "title": "Top K Frequent Elements",
      "platform": "LeetCode",
      "difficulty": "Medium",
      "url": "https://leetcode.com/problems/top-k-frequent-elements/",
      "urlGenerated": false,
      "primaryTopic": "Sorting",
      "pattern": "Top K Elements",
      "notes": "Bucket Sort\n\nminheap that's kept at size k, if its bigger than k pop the min, by the end it should be left with k largest",
      "metadata": {
        "companies": [],
        "frequency": null,
        "sources": [
          "Aryan-dsa-160",
          "blind-75",
          "dsa-patterns-cheat-sheet",
          "grind-75",
          "neetcode-150"
        ]
      },
      "progress": {
        "completed": false,
        "attemptedButNotSolved": false,
        "hasSolution": false,
        "hasOptimalSolution": false,
        "understoodCompletely": false,
        "needsReview": false,
        "solvedOnce": false,
        "solvedTwice": false,
        "solvedThreePlus": false,
        "bookmarked": false,
        "isFavorite": false,
        "watchedVideoSolution": false,
        "readEditorialSolution": false,
        "solvedInTime": false,
        "needsSpeedImprovement": false,
        "canExplainToOthers": false,
        "interviewReady": false,
        "markedForRevision": false,
        "revisedOnce": false,
        "revisedMultipleTimes": false,
        "easierThanRated": false,
        "harderThanRated": false,
        "hasNotes": false,
        "hasCustomTags": false
      },
      "timestamps": {
        "firstAttemptedAt": null,
        "lastAttemptedAt": null,
        "completedAt": null,
        "lastReviewedAt": null,
        "addedToFavoritesAt": null
      },
      "userData": {
        "notes": "",
        "customTags": [],
        "timeTaken": null,
        "attemptCount": 0,
        "personalDifficultyRating": null,
        "confidenceLevel": null,
        "solutionLinks": [],
        "resourceLinks": [],
        "mistakesMade": [],
        "keyInsights": []
      }
    },
    {
      "id": "leetcode-first-missing-positive",
      "title": "First Missing Positive",
      "platform": "LeetCode",
      "difficulty": "Hard",
      "url": "https://leetcode.com/problems/first-missing-positive/",
      "urlGenerated": false,
      "primaryTopic": "Sorting",
      "pattern": "Divide and Conquer",
      "notes": "Day 4",
      "metadata": {
        "companies": [
          "Amazon"
        ],
        "frequency": null,
        "sources": [
          "Aryan-dsa-160",
          "amazon-sde-riddhi-dutta"
        ],
        "importance": "VVVI",
        "day": 4
      },
      "progress": {
        "completed": false,
        "attemptedButNotSolved": false,
        "hasSolution": false,
        "hasOptimalSolution": false,
        "understoodCompletely": false,
        "needsReview": false,
        "solvedOnce": false,
        "solvedTwice": false,
        "solvedThreePlus": false,
        "bookmarked": false,
        "isFavorite": false,
        "watchedVideoSolution": false,
        "readEditorialSolution": false,
        "solvedInTime": false,
        "needsSpeedImprovement": false,
        "canExplainToOthers": false,
        "interviewReady": false,
        "markedForRevision": false,
        "revisedOnce": false,
        "revisedMultipleTimes": false,
        "easierThanRated": false,
        "harderThanRated": false,
        "hasNotes": false,
        "hasCustomTags": false
      },
      "timestamps": {
        "firstAttemptedAt": null,
        "lastAttemptedAt": null,
        "completedAt": null,
        "lastReviewedAt": null,
        "addedToFavoritesAt": null
      },
      "userData": {
        "notes": "",
        "customTags": [],
        "timeTaken": null,
        "attemptCount": 0,
        "personalDifficultyRating": null,
        "confidenceLevel": null,
        "solutionLinks": [],
        "resourceLinks": [],
        "mistakesMade": [],
        "keyInsights": []
      }
    },
    {
      "id": "leetcode-maximum-gap",
      "title": "Maximum Gap",
      "platform": "LeetCode",
      "difficulty": "Hard",
      "url": "https://www.google.com/search?q=Maximum+Gap+LeetCode",
      "urlGenerated": true,
      "primaryTopic": "Sorting",
      "pattern": "Top K Elements",
      "notes": "Radix Sort",
      "metadata": {
        "companies": [],
        "frequency": null,
        "sources": [
          "Aryan-dsa-160"
        ]
      },
      "progress": {
        "completed": false,
        "attemptedButNotSolved": false,
        "hasSolution": false,
        "hasOptimalSolution": false,
        "understoodCompletely": false,
        "needsReview": false,
        "solvedOnce": false,
        "solvedTwice": false,
        "solvedThreePlus": false,
        "bookmarked": false,
        "isFavorite": false,
        "watchedVideoSolution": false,
        "readEditorialSolution": false,
        "solvedInTime": false,
        "needsSpeedImprovement": false,
        "canExplainToOthers": false,
        "interviewReady": false,
        "markedForRevision": false,
        "revisedOnce": false,
        "revisedMultipleTimes": false,
        "easierThanRated": false,
        "harderThanRated": false,
        "hasNotes": false,
        "hasCustomTags": false
      },
      "timestamps": {
        "firstAttemptedAt": null,
        "lastAttemptedAt": null,
        "completedAt": null,
        "lastReviewedAt": null,
        "addedToFavoritesAt": null
      },
      "userData": {
        "notes": "",
        "customTags": [],
        "timeTaken": null,
        "attemptCount": 0,
        "personalDifficultyRating": null,
        "confidenceLevel": null,
        "solutionLinks": [],
        "resourceLinks": [],
        "mistakesMade": [],
        "keyInsights": []
      }
    }
  ]
}